test/__init__.py
test/test_torip.py
torip/__init__.py
torip/exceptions.py
torip/ipapis.py
torip/locator.py
torip/utilities.py
torip-0.2.2.dist-info/LICENSE
torip-0.2.2.dist-info/METADATA
torip-0.2.2.dist-info/WHEEL
torip-0.2.2.dist-info/top_level.txt
torip-0.2.2.dist-info/RECORD
