Metadata-Version: 2.1
Name: torip
Version: 0.2.2
Summary: Library for Tornado web framework to locate IPs or server names.
Home-page: https://github.com/mendrugory/torip
Author: Gonzalo Gabriel Jiménez Fuentes
Author-email: iam@mendrugory.com
License: MIT License
Keywords: Tornado IP Locate
Platform: UNKNOWN
Classifier: Development Status :: 4 - Beta
Classifier: Topic :: Utilities
Classifier: License :: OSI Approved :: MIT License
Classifier: Intended Audience :: Developers
License-File: LICENSE
Requires-Dist: tornado
